rtf-converter/__init__.py
rtf-converter/rtf_converter.py
rtf_converter/__init__.py
rtf_converter/rtf_converter.py
rtf_converter-0.1.22.dist-info/LICENSE.md
rtf_converter-0.1.22.dist-info/METADATA
rtf_converter-0.1.22.dist-info/WHEEL
rtf_converter-0.1.22.dist-info/top_level.txt
rtf_converter-0.1.22.dist-info/RECORD
