Metadata-Version: 2.1
Name: rtf-converter
Version: 0.1.22
Summary: Easily convert RTF to plain text format - Supports Javascript, Python, CSharp and PHP.
License-File: LICENSE.md
